README.rst
setup.py
backupmysystemusb2usb/__init__.py
backupmysystemusb2usb/backup_system.py
backupmysystemusb2usb/blkid.py
backupmysystemusb2usb/const.py
backupmysystemusb2usb/dd.py
backupmysystemusb2usb/e2label.py
backupmysystemusb2usb/gui.py
backupmysystemusb2usb/kill_dd.py
backupmysystemusb2usb/print_log.py
backupmysystemusb2usb/umount.py
backupmysystemusb2usb/usb2usb.py
backupmysystemusb2usb.egg-info/PKG-INFO
backupmysystemusb2usb.egg-info/SOURCES.txt
backupmysystemusb2usb.egg-info/dependency_links.txt
backupmysystemusb2usb.egg-info/not-zip-safe
backupmysystemusb2usb.egg-info/requires.txt
backupmysystemusb2usb.egg-info/top_level.txt