Metadata-Version: 1.2
Name: backupmysystemusb2usb
Version: 1.0.1
Summary: Backup a usb key to another usb key with the same space disk
Home-page: https://github.com/stephaneworkspace/backupmysystemusb2usb.git
Author: Stéphane Bressani
Author-email: s.bressani@bluewin.ch
License: GPLv3+
Platform: UNKNOWN
Classifier: Development Status :: 4 - Beta
Classifier: Environment :: No Input/Output (Daemon)
Classifier: Environment :: X11 Applications :: GTK
Classifier: Intended Audience :: Developers
Classifier: Natural Language :: English
Classifier: License :: OSI Approved :: GNU Lesser General Public License v3 or later (LGPLv3+)
Classifier: Operating System :: POSIX :: Linux
Classifier: Programming Language :: Python
Classifier: Programming Language :: Python :: 3.7
Classifier: Topic :: System :: Archiving :: Backup
Classifier: Topic :: System :: Archiving :: Mirroring
Classifier: Topic :: Utilities
Requires-Python: >=3.7
